dash_extensions/BeforeAfter.py
dash_extensions/CycleBreaker.py
dash_extensions/DeferScript.py
dash_extensions/EventListener.py
dash_extensions/EventSource.py
dash_extensions/Keyboard.py
dash_extensions/Loading.py
dash_extensions/Lottie.py
dash_extensions/Mermaid.py
dash_extensions/Purify.py
dash_extensions/SSE.py
dash_extensions/WebSocket.py
dash_extensions/__init__.py
dash_extensions/_imports_.py
dash_extensions/async-BeforeAfter.js
dash_extensions/async-Lottie.js
dash_extensions/async-Mermaid.js
dash_extensions/async-Purify.js
dash_extensions/async-SSE.js
dash_extensions/async-null.js
dash_extensions/dash_extensions.js
dash_extensions/enrich.py
dash_extensions/events.py
dash_extensions/javascript.py
dash_extensions/logging.py
dash_extensions/metadata.json
dash_extensions/package-info.json
dash_extensions/pages.py
dash_extensions/proptypes.js
dash_extensions/snippets.py
dash_extensions/streaming.py
dash_extensions/utils.py
dash_extensions/validate.py
dash_extensions-2.0.3.dist-info/licenses/LICENSE
dash_extensions-2.0.3.dist-info/METADATA
dash_extensions-2.0.3.dist-info/WHEEL
dash_extensions-2.0.3.dist-info/top_level.txt
dash_extensions-2.0.3.dist-info/RECORD
