Metadata-Version: 2.4
Name: dash-extensions
Version: 2.0.3
Summary: Extensions for Plotly Dash.
Author: Emil Haldrup Eriksen <emil.h.eriksen@gmail.com>
Author-email: emher <emil.h.eriksen@gmail.com>
License-Expression: MIT
Project-URL: homepage, https://dash-extensions.com
Project-URL: repository, https://github.com/emilhe/dash-extensions
Requires-Python: >=3.11
License-File: LICENSE
Requires-Dist: dash>=3.0.0
Requires-Dist: more-itertools>=10.6.0
Requires-Dist: jsbeautifier>=1.15.4
Requires-Dist: Flask-Caching>=2.3.1
Requires-Dist: dataclass-wizard>=0.35.0
Requires-Dist: pydantic>=2.10.6
Dynamic: author
Dynamic: license-file
